sqlpy/__init__.py
sqlpy/config.py
sqlpy/exceptions.py
sqlpy/sqlpy.py
sqlpy-0.3.5.dist-info/DESCRIPTION.rst
sqlpy-0.3.5.dist-info/METADATA
sqlpy-0.3.5.dist-info/RECORD
sqlpy-0.3.5.dist-info/WHEEL
sqlpy-0.3.5.dist-info/entry_points.txt
sqlpy-0.3.5.dist-info/metadata.json
sqlpy-0.3.5.dist-info/top_level.txt
