Metadata-Version: 2.0
Name: sqlpy
Version: 0.3.5
Summary: Write actual SQL to retrieve your data.
Home-page: https://github.com/9fin/sqlpy
Author: 9fin
Author-email: oss@9fin.com
License: MIT
Download-URL: https://github.com/9fin/sqlpy/archive/0.1.tar.gz
Keywords: sql,python,postgres,postgresql,mysql,sqlite
Platform: UNKNOWN
Classifier: Development Status :: 4 - Beta
Classifier: Intended Audience :: Developers
Classifier: License :: OSI Approved :: MIT License
Classifier: Programming Language :: Python :: 2
Classifier: Programming Language :: Python :: 3
